<?xml version="1.0" encoding="UTF-8"?>

<databaseChangeLog xmlns="http://www.liquibase.org/xml/ns/dbchangelog"
	xmlns:xsi="http://www.w3.org/2001/XMLSchema-instance"
	xsi:schemaLocation="http://www.liquibase.org/xml/ns/dbchangelog http://www.liquibase.org/xml/ns/dbchangelog/dbchangelog-3.1.xsd"
	logicalFilePath="database/project_model.xml">

	<!-- MySQL DB is supported from liquibase perspective but JPA  layer is not working due to SEQ -->
	<property name="autoIncrement" value="true" dbms="mysql"/>
	<property name="autoIncrement" value="false" dbms="oracle"/>
	<property name="autoIncrement" value="false" dbms="postgresql"/>
	<property name="autoIncrement" value="false" dbms="h2"/>

	<property name="varcharUnit" value="CHAR" dbms="oracle"/>
	<property name="varcharUnit" value="" dbms="mysql,postgresql,h2"/>

	<include file="schema/model.xml" relativeToChangelogFile="true" />
	<include file="data/data.xml" relativeToChangelogFile="true" />
	<include file="schema/20.6.0/model.xml" relativeToChangelogFile="true" />
	<include file="data/20.6.0/data.xml" relativeToChangelogFile="true" />
	<include file="schema/20.7.0/model.xml" relativeToChangelogFile="true" />
	<include file="data/20.7.0/data.xml" relativeToChangelogFile="true" />
	<include file="schema/21.0.0/model.xml" relativeToChangelogFile="true" />
	<include file="schema/22.0.0/model.xml" relativeToChangelogFile="true" />
	<include file="data/22.0.0/data.xml" relativeToChangelogFile="true" />
	<include file="data/23.0.0/data.xml" relativeToChangelogFile="true"/>
	<include file="schema/23.3.0/model.xml" relativeToChangelogFile="true" />
	<include file="schema/25.0.0/model.xml" relativeToChangelogFile="true" />
	<include file="schema/26.0.0/model.xml" relativeToChangelogFile="true" />
	<include file="data/27.0.0/model.xml" relativeToChangelogFile="true" />
	<include file="schema/27.0.0/model.xml" relativeToChangelogFile="true" />
	<include file="schema/28.0.0/model.xml" relativeToChangelogFile="true" />
	<include file="schema/29.0.0/model.xml" relativeToChangelogFile="true" />
	<include file="schema/30.0.0/model.xml" relativeToChangelogFile="true" />
	<include file="schema/31.0.0/model.xml" relativeToChangelogFile="true" />
	<include file="data/31.0.0/data.xml" relativeToChangelogFile="true"/>
	<include file="schema/31.1.0/model.xml" relativeToChangelogFile="true" />
	<include file="schema/32.0.0/model.xml" relativeToChangelogFile="true" />
	<include file="schema/33.0.0/model.xml" relativeToChangelogFile="true" />
	<include file="data/33.0.0/data.xml" relativeToChangelogFile="true" />
	<include file="schema/34.0.0/model.xml" relativeToChangelogFile="true" />
	<include file="data/34.0.0/data.xml" relativeToChangelogFile="true" />
	<include file="schema/35.0.0/model.xml" relativeToChangelogFile="true" />
	<include file="data/35.0.0/data.xml" relativeToChangelogFile="true" />
	<include file="schema/36.0.0/model.xml" relativeToChangelogFile="true" />
	<include file="schema/37.0.0/model.xml" relativeToChangelogFile="true" />
	<include file="schema/37.0.0/qapi.xml" relativeToChangelogFile="true" />
	<include file="schema/38.0.0/model.xml" relativeToChangelogFile="true" />
	<include file="schema/39.0.0/model.xml" relativeToChangelogFile="true" />

	<include file="org/quartz/impl/jdbcjobstore/liquibase.quartz.init.xml" relativeToChangelogFile="false" />

</databaseChangeLog>
